pzip_storage/__init__.py
pzip_storage/management/__init__.py
pzip_storage/management/commands/__init__.py
pzip_storage/management/commands/rotate_storage.py
django_pzip_storage-1.3.0.dist-info/WHEEL
django_pzip_storage-1.3.0.dist-info/METADATA
django_pzip_storage-1.3.0.dist-info/RECORD
