Metadata-Version: 2.3
Name: django-pzip-storage
Version: 1.3.0
Summary: Storage backend for Django that encrypts/compresses with PZip.
Author: Dan Watson
Author-email: Dan Watson <watsond@imsweb.com>
License: MIT
Classifier: Development Status :: 4 - Beta
Classifier: Intended Audience :: Developers
Classifier: License :: OSI Approved :: MIT License
Classifier: Programming Language :: Python
Classifier: Programming Language :: Python :: 3
Requires-Dist: pzip>=1.2.0
Requires-Python: >=3.10
Project-URL: Homepage, https://github.com/imsweb/django-pzip-storage
